{
    "data": [
        {
            "name": "intro",
            "heading" : "What I Offer",
            "desc":"I am a dedicated full-stack developer with a keen eye for design and a passion for creating intuitive and efficient digital solutions. My expertise spans across websites, UI designs, and iOS apps.",

            "type": "items",
            "action": {
                "name": "openURL",
                "type" : "link"
            },
            "items": [
                {
                    "id": 1,
                    "name": "Websites",
                    "desc": "I specialize in developing responsive and user-friendly websites that are tailored to meet the unique needs of each client. From concept to deployment.",
                    "tags": [
                        "Responsive Design",
                        "SEO Optimization",
                        "Performance Tuning",
                        "Custom Web Solutions",
                        "E-commerce Integration",
                        "Cross-Browser"
                    ]
                },
                {
                    "id": 2,
                    "name": "UI Designs",
                    "desc": "My approach to UI design is centered on creating visually appealing and user-centric interfaces. I strive to design layouts that are both aesthetically pleasing and highly functional, enhancing the overall user experience.",
                    "tags": [
                        "User Research",
                        "Wireframing",
                        "Prototyping",
                        "Visual Design",
                        "Usability Testing",
                        "Interaction Design"
                    ]
                }, 
                {
                    "id": 3,
                    "name": "iOS Apps",
                    "desc": "With a strong background in iOS development, I create robust and scalable apps that offer seamless user experiences. My focus is on leveraging the latest technologies to build apps that are not only functional but also engaging.",
                    "tags": [
                        "Swift",
                        "Objective-C",
                        "User Interface Design",
                        "Firebase Integration",
                        "Optimization",
                        "App Store Deployment"
                    ]
                }
            ]
        }
    ]
}
